countmut/__init__.py
countmut/bam_tags.py
countmut/cli.py
countmut/core.py
countmut/utils.py
countmut-0.0.8.dist-info/licenses/LICENSE
countmut-0.0.8.dist-info/METADATA
countmut-0.0.8.dist-info/WHEEL
countmut-0.0.8.dist-info/entry_points.txt
countmut-0.0.8.dist-info/top_level.txt
countmut-0.0.8.dist-info/RECORD
